odoo/addons/state_sales_team_pricelist/README.rst
odoo/addons/state_sales_team_pricelist/__init__.py
odoo/addons/state_sales_team_pricelist/__manifest__.py
odoo/addons/state_sales_team_pricelist/i18n/es.po
odoo/addons/state_sales_team_pricelist/models/__init__.py
odoo/addons/state_sales_team_pricelist/models/product_pricelist.py
odoo/addons/state_sales_team_pricelist/models/sale_order.py
odoo/addons/state_sales_team_pricelist/static/description/icon.png
odoo/addons/state_sales_team_pricelist/views/product_pricelist_views.xml
odoo_addon_state_sales_team_pricelist-15.0.1.0.0.2.dist-info/METADATA
odoo_addon_state_sales_team_pricelist-15.0.1.0.0.2.dist-info/WHEEL
odoo_addon_state_sales_team_pricelist-15.0.1.0.0.2.dist-info/top_level.txt
odoo_addon_state_sales_team_pricelist-15.0.1.0.0.2.dist-info/RECORD
